durga/__init__.py
durga/collection.py
durga/element.py
durga/resource.py
durga-0.1.0.dist-info/DESCRIPTION.rst
durga-0.1.0.dist-info/METADATA
durga-0.1.0.dist-info/metadata.json
durga-0.1.0.dist-info/RECORD
durga-0.1.0.dist-info/top_level.txt
durga-0.1.0.dist-info/WHEEL
