Metadata-Version: 2.0
Name: durga
Version: 0.1.0
Summary: Create easy to use Python objects for REST resources including schema validation.
Home-page: https://github.com/transcode-de/durga
Author: transcode
Author-email: team@transcode.de
License: BSD
Keywords: durga
Platform: UNKNOWN
Classifier: Development Status :: 4 - Beta
Classifier: Intended Audience :: Developers
Classifier: License :: OSI Approved :: BSD License
Classifier: Natural Language :: English
Classifier: Programming Language :: Python :: 2
Classifier: Programming Language :: Python :: 2.7
Classifier: Programming Language :: Python :: 3
Classifier: Programming Language :: Python :: 3.4
Requires-Dist: schema (>=0.3.1)
Requires-Dist: requests (>=2.5.0)
